styledctk_widgets/__about__.py
styledctk_widgets/__init__.py
styledctk_widgets/__main__.py
styledctk_widgets/CTK_Buttons/CTK_Button_styles.py
styledctk_widgets/CTK_Buttons/SCTkButton.py
styledctk_widgets/CTK_Buttons/__init__.py
styledctk_widgets/CTK_Entrys/CTK_Entry_styles.py
styledctk_widgets/CTK_Entrys/SCTKEntry.py
styledctk_widgets/CTK_Entrys/__init__.py
styledctk_widgets/cli/__init__.py
styledctk_widgets-0.0.2.dist-info/METADATA
styledctk_widgets-0.0.2.dist-info/WHEEL
styledctk_widgets-0.0.2.dist-info/entry_points.txt
styledctk_widgets-0.0.2.dist-info/licenses/LICENSE
styledctk_widgets-0.0.2.dist-info/RECORD
